stackit/resourcemanager/__init__.py
stackit/resourcemanager/api/__init__.py
stackit/resourcemanager/api/default_api.py
stackit/resourcemanager/api_client.py
stackit/resourcemanager/api_response.py
stackit/resourcemanager/configuration.py
stackit/resourcemanager/exceptions.py
stackit/resourcemanager/models/__init__.py
stackit/resourcemanager/models/create_folder_payload.py
stackit/resourcemanager/models/create_project_payload.py
stackit/resourcemanager/models/error_response.py
stackit/resourcemanager/models/folder_response.py
stackit/resourcemanager/models/get_folder_details_response.py
stackit/resourcemanager/models/get_project_response.py
stackit/resourcemanager/models/lifecycle_state.py
stackit/resourcemanager/models/list_folders_response.py
stackit/resourcemanager/models/list_folders_response_items_inner.py
stackit/resourcemanager/models/list_organizations_response.py
stackit/resourcemanager/models/list_organizations_response_items_inner.py
stackit/resourcemanager/models/list_projects_response.py
stackit/resourcemanager/models/member.py
stackit/resourcemanager/models/organization_response.py
stackit/resourcemanager/models/parent.py
stackit/resourcemanager/models/parent_list_inner.py
stackit/resourcemanager/models/partial_update_folder_payload.py
stackit/resourcemanager/models/partial_update_organization_payload.py
stackit/resourcemanager/models/partial_update_project_payload.py
stackit/resourcemanager/models/project.py
stackit/resourcemanager/py.typed
stackit/resourcemanager/rest.py
stackit_resourcemanager-0.6.1.dist-info/METADATA
stackit_resourcemanager-0.6.1.dist-info/WHEEL
stackit_resourcemanager-0.6.1.dist-info/licenses/LICENSE.md
stackit_resourcemanager-0.6.1.dist-info/licenses/NOTICE.txt
stackit_resourcemanager-0.6.1.dist-info/RECORD
